{"nodes":[{"key":4,"text":"go to garage","breakdownLabel":"⚡","evidence":"D0-36","color":"lightyellow","category":"step","isGroup":false},{"key":2,"text":"walk over / get a ride to police station","evidence":"D0-34","color":"lightyellow","category":"step","isGroup":false},{"key":1,"text":"park away from garage","breakdownLabel":"⚡","evidence":"D0-33","color":"lightyellow","category":"step","isGroup":false},{"key":3,"text":"check in + paper work","evidence":"D0-35","color":"lightyellow","category":"step","isGroup":false},{"key":9,"text":"go to morewood","evidence":"D0-42","color":"lightyellow","category":"step","isGroup":false},{"key":10,"text":"do route A/B","evidence":"D0-56","color":"lightyellow","category":"step","isGroup":false},{"key":8,"text":"has gas?","evidence":"D0-37","color":"lightpink","category":"diamond","isGroup":false},{"key":12,"text":"write down passenger count","evidence":"D0-55","color":"lightyellow","category":"step","isGroup":false},{"key":5,"text":"maintenance check","evidence":"D0-39","color":"lightyellow","category":"step","isGroup":false},{"key":17,"text":"return paper work","evidence":"D0-46","color":"lightyellow","category":"step","isGroup":false},{"key":11,"text":"last route / end shift","evidence":"D0-43","color":"lightyellow","category":"step","isGroup":false},{"key":13,"text":"take a break","evidence":"D0-47","color":"lightyellow","category":"step","isGroup":false},{"key":14,"text":"get gas @ shell","evidence":"D0-38","color":"lightyellow","category":"step","isGroup":false},{"key":6,"text":"needs work done?","evidence":"D0-40","color":"lightpink","category":"diamond","isGroup":false},{"key":15,"text":"fill more paperwork","evidence":"D0-44","color":"lightyellow","category":"step","isGroup":false},{"key":16,"text":"hand off bus","evidence":"D0-45","color":"lightyellow","category":"step","isGroup":false},{"key":7,"text":"give to shift coordinator","evidence":"D0-41","color":"lightyellow","category":"step","isGroup":false}],"links":[{"from":4,"to":5,"color":"black","text":"","category":"nolabel"},{"from":2,"to":3,"color":"black","text":"","category":"nolabel"},{"from":1,"to":2,"color":"black","text":"","category":"nolabel"},{"from":3,"to":4,"color":"black","text":"","category":"nolabel"},{"from":9,"to":10,"color":"black","text":"","category":"nolabel"},{"from":10,"to":12,"color":"black","text":"","category":"nolabel"},{"from":10,"to":11,"color":"black","text":"T: 2:45pm ","category":"label"},{"from":8,"to":9,"color":"black","text":"Y","category":"label"},{"from":8,"to":14,"color":"black","text":"N","category":"label"},{"from":12,"to":13,"color":"black","text":"","category":"no label"},{"from":5,"to":6,"color":"black","text":"","category":"nolabel"},{"from":11,"to":15,"color":"black","text":"","category":"nolabel"},{"from":13,"to":14,"color":"black","text":"T: no gas E: D0-37","category":"label"},{"from":14,"to":9,"color":"black","text":"","category":"nolabel"},{"from":6,"to":7,"color":"black","text":"Y","category":"label"},{"from":6,"to":8,"color":"black","text":"N","category":"label"},{"from":15,"to":16,"color":"black","text":"","category":"nolabel"},{"from":16,"to":17,"color":"black","text":"","category":"nolabel"},{"from":7,"to":8,"color":"black","text":"","category":"nolabel"}]}